jayson/__init__.py
jayson/__main__.py
jayson/hooking/__init__.py
jayson/hooking/ante_build_hook.py
jayson/hooking/ante_release_hook.py
jayson/hooking/post_build_hook.py
jayson/hooking/post_release_hook.py
jayson/pyrustic_data/hooking.json
jayson/pyrustic_data/hubstore.json
jayson/pyrustic_data/release_info.json
secret/SCRATCH.py
secret/__init__.py
tests/__init__.py
jayson-0.0.2.dist-info/LICENSE
jayson-0.0.2.dist-info/METADATA
jayson-0.0.2.dist-info/WHEEL
jayson-0.0.2.dist-info/entry_points.txt
jayson-0.0.2.dist-info/top_level.txt
jayson-0.0.2.dist-info/RECORD
