Metadata-Version: 2.1
Name: jayson
Version: 0.0.2
Summary: Intuitive interaction with JSON files
Home-page: https://github.com/pyrustic/jayson
Author: Pyrustic Evangelist
Author-email: pyrustic@protonmail.com
Maintainer: Pyrustic Evangelist
Maintainer-email: pyrustic@protonmail.com
License: MIT
Keywords: library,json,data,configuration
Platform: UNKNOWN
Classifier: Programming Language :: Python :: 3
Classifier: License :: OSI Approved :: MIT License
Classifier: Operating System :: OS Independent
Requires-Python: >=3.5
